{"trial_id": "3", "hyperparameters": {"space": [{"class_name": "Int", "config": {"name": "units", "default": null, "conditions": [], "min_value": 32, "max_value": 128, "step": 32, "sampling": "linear"}}, {"class_name": "Choice", "config": {"name": "learning_rate", "default": 0.01, "conditions": [], "values": [0.01, 0.001, 0.0001], "ordered": true}}], "values": {"units": 96, "learning_rate": 0.001}}, "metrics": {"metrics": {"loss": {"direction": "min", "observations": [{"value": [0.8166207273801168], "step": 7}]}, "accuracy": {"direction": "max", "observations": [{"value": [0.6798046032587687], "step": 7}]}, "val_loss": {"direction": "min", "observations": [{"value": [0.7195345759391785], "step": 7}]}, "val_accuracy": {"direction": "max", "observations": [{"value": [0.7299983104070028], "step": 7}]}}}, "score": 0.7299983104070028, "best_step": 7, "status": "COMPLETED", "message": null}